{
  "revision_date": "2026-06-20",
  "platforms": ["base44", "vercel", "supabase-edge-functions", "cloudflare-workers", "cloudflare-pages-functions"],
  "functions": [
    "adminGhostAccounts",
    "adminUpdateEntity",
    "api/hello",
    "api/register",
    "biweeklyReport",
    "capturePaypalPayment",
    "captureTier1Payment",
    "completePayment",
    "connectSellerPaypal",
    "copyrightViolationAlert",
    "createManagedAccount",
    "createPaypalOrder",
    "createSupabaseUpload",
    "createTier1Order",
    "dailyUpdatesEmail",
    "deleteListingPermanent",
    "getPaypalConfig",
    "getSellerPaypalStatus",
    "logLogin",
    "loginAsGhost",
    "moderateListing",
    "notifyNewContent",
    "notifyNewMember",
    "salesNotification",
    "sendDailyRewardEmail",
    "sendOrderNotification",
    "sendPaypalGuideEmail",
    "setKevinTestProfilePicture",
    "test",
    "testSupabaseListingUpload",
    "updateProfileMedia",
    "uploadToR2",
    "verifyPaymentStatus"
  ],
  "required_environment": {
    "all_adapters": ["BASE44_FUNCTION_BASE_URL"],
    "payments": ["STRIPE_SECRET_KEY", "STRIPE_PUBLISHABLE_KEY", "PAYPAL_CLIENT_ID", "PAYPAL_CLIENT_SECRET"],
    "storage": ["SUPABASE_SERVICE_ROLE_KEY", "VITE_SUPABASE_URL", "VITE_SUPABASE_ANON_KEY"]
  }
}